[
  {
    "id": 1,
    "brand": "Toyota",
    "model": "Camry",
    "year": 2022,
    "color": "Silver",
    "date": "2022-12-01"
  },
  {
    "id": 2,
    "brand": "Honda",
    "model": "Civic",
    "year": 2022,
    "color": "Blue",
    "date": "2022-11-15"
  },
  {
    "id": 3,
    "brand": "Ford",
    "model": "Escape",
    "year": 2023,
    "color": "Red",
    "date": "2023-01-10"
  },
  {
    "id": 4,
    "brand": "Chevrolet",
    "model": "Malibu",
    "year": 2022,
    "color": "Black",
    "date": "2022-10-05"
  },
  {
    "id": 5,
    "brand": "Nissan",
    "model": "Altima",
    "year": 2022,
    "color": "White",
    "date": "2022-09-20"
  },
  {
    "id": 6,
    "brand": "BMW",
    "model": "X5",
    "year": 2023,
    "color": "Gray",
    "date": "2023-03-25"
  },
  {
    "id": 7,
    "brand": "Mercedes-Benz",
    "model": "E-Class",
    "year": 2022,
    "color": "Green",
    "date": "2022-08-12"
  },
  {
    "id": 8,
    "brand": "Audi",
    "model": "A4",
    "year": 2022,
    "color": "Silver",
    "date": "2022-07-03"
  },
  {
    "id": 9,
    "brand": "Hyundai",
    "model": "Tucson",
    "year": 2023,
    "color": "Blue",
    "date": "2023-02-18"
  },
  {
    "id": 10,
    "brand": "Kia",
    "model": "Sportage",
    "year": 2022,
    "color": "Red",
    "date": "2022-06-09"
  },
  {
    "id": 11,
    "brand": "Tesla",
    "model": "Model 3",
    "year": 2023,
    "color": "Black",
    "date": "2023-04-30"
  },
  {
    "id": 12,
    "brand": "Subaru",
    "model": "Outback",
    "year": 2022,
    "color": "White",
    "date": "2022-05-15"
  },
  {
    "id": 13,
    "brand": "Lexus",
    "model": "RX",
    "year": 2022,
    "color": "Gray",
    "date": "2022-04-22"
  }
]
